streamlit_chat_widget/__init__.py
streamlit_chat_widget/frontend/build/asset-manifest.json
streamlit_chat_widget/frontend/build/bootstrap.min.css
streamlit_chat_widget/frontend/build/index.html
streamlit_chat_widget/frontend/build/static/css/main.f18aa276.css
streamlit_chat_widget/frontend/build/static/css/main.f18aa276.css.map
streamlit_chat_widget/frontend/build/static/css/main.fc235b66.css
streamlit_chat_widget/frontend/build/static/css/main.fc235b66.css.map
streamlit_chat_widget/frontend/build/static/js/main.5b2dd53c.js
streamlit_chat_widget/frontend/build/static/js/main.5b2dd53c.js.LICENSE.txt
streamlit_chat_widget/frontend/build/static/js/main.5b2dd53c.js.map
streamlit_chat_widget/frontend/build/static/js/main.b2693a7e.js
streamlit_chat_widget/frontend/build/static/js/main.b2693a7e.js.LICENSE.txt
streamlit_chat_widget/frontend/build/static/js/main.b2693a7e.js.map
streamlit_chat_widget/frontend/build/static/js/main.f461ee52.js
streamlit_chat_widget/frontend/build/static/js/main.f461ee52.js.LICENSE.txt
streamlit_chat_widget/frontend/build/static/js/main.f461ee52.js.map
streamlit_chat_widget-0.2.0.dist-info/LICENSE
streamlit_chat_widget-0.2.0.dist-info/METADATA
streamlit_chat_widget-0.2.0.dist-info/WHEEL
streamlit_chat_widget-0.2.0.dist-info/top_level.txt
streamlit_chat_widget-0.2.0.dist-info/RECORD
