Metadata-Version: 2.1
Name: streamlit_chat_widget
Version: 0.2.0
Summary: A custom chat input widget for Streamlit
Home-page: https://github.com/yourusername/streamlit_chat_widget
Author: Mohammed Bahageel
Author-email: youremail@example.com
Classifier: Programming Language :: Python :: 3
Classifier: License :: OSI Approved :: MIT License
Classifier: Operating System :: OS Independent
Requires-Python: >=3.6
License-File: LICENSE
Requires-Dist: streamlit>=1.0
